oracle/__init__.py
oracle/tools/__init__.py
oracle/tools/query.py
oracle/tools/utils.py
oracle/yamls/query.yaml
tests/__init__.py
tests/test_query.py
pforacle-0.0.6.dist-info/METADATA
pforacle-0.0.6.dist-info/WHEEL
pforacle-0.0.6.dist-info/entry_points.txt
pforacle-0.0.6.dist-info/top_level.txt
pforacle-0.0.6.dist-info/RECORD
