Metadata-Version: 2.1
Name: pforacle
Version: 0.0.6
Summary: This package contains prompt flow tools for querying Oracle databases.
Requires-Dist: oracledb
